ndStepwise/__init__.py
ndStepwise/__main__.py
ndStepwise/all_tree_regression.py
ndStepwise/all_tree_structures.py
ndStepwise/basic_regression.py
ndStepwise/blah.py
ndStepwise/check_cutoff_code.py
ndStepwise/check_layered_regression.py
ndStepwise/clean_layered_regression.py
ndStepwise/digits_handwritten.py
ndStepwise/find_tree_structs.py
ndStepwise/graphing_tree.py
ndStepwise/installing_datasets.py
ndStepwise/new_stepwise_regression.py
ndStepwise/process_inputs.py
ndStepwise/recheck_bok_improv_v2.py
ndStepwise/run_all_datasets_premade_models.py
ndStepwise/run_all_possible_trees.py
ndStepwise/run_datasets_inner_kfold_only.py
ndStepwise/run_datasets_kfolds.py
ndStepwise/run_datasets_outter_kfolds.py
ndStepwise/run_datasets_regular.py
ndStepwise/run_individual_tree.py
ndStepwise/run_mnist.py
ndStepwise/run_single_datasets.py
ndStepwise/run_single_datasets_kfolds.py
ndStepwise/run_single_datasets_thread.py
ndStepwise/run_with_real_data.py
ndStepwise/stepwise_model_selection.py
ndStepwise/test_bok_improved_method.py
ndStepwise/test_tree_encoding.py
ndStepwise/timing_script.py
ndStepwise/whole_tree_from_nodes.py
ndStepwise/includes/__init__.py
ndStepwise/includes/config.py
ndStepwise/includes/logging.py
ndStepwise/includes/model.py
ndStepwise/includes/model_functions.py
ndStepwise/logs/model_functions.py
ndStepwise/venv/Scripts/pywin32_postinstall.py
ndStepwise/venv/Scripts/pywin32_testall.py
ndStepwise-1.0.4.dist-info/METADATA
ndStepwise-1.0.4.dist-info/WHEEL
ndStepwise-1.0.4.dist-info/entry_points.txt
ndStepwise-1.0.4.dist-info/top_level.txt
ndStepwise-1.0.4.dist-info/RECORD
