Metadata-Version: 2.2
Name: ndStepwise
Version: 1.0.4
Summary: A package to perform ND Stepwise regression for multiclass problems.
Author-email: Maxwell Dix-Matthews <maxdixmatthews@gmail.com>
Project-URL: Homepage, https://github.com/maxdixmatthews/multiclass-regression
Classifier: Programming Language :: Python :: 3
Classifier: Operating System :: OS Independent
Requires-Dist: matplotlib==3.7.4
Requires-Dist: numpy===1.26.0
Requires-Dist: pandas>=1.5.2
Requires-Dist: plotly==4.3.0
Requires-Dist: pydot==2.0.0
Requires-Dist: scikit-optimize==0.10.2
Requires-Dist: scikit-plot==0.3.7
Requires-Dist: scikit-learn==1.5.2
Requires-Dist: virtualenv==20.4.3
Requires-Dist: wheel==0.45.1
Requires-Dist: ucimlrepo==0.0.7
Requires-Dist: tensorflow==2.18.0
Requires-Dist: xgboost==2.1.3
Requires-Dist: scipy==1.11.4
Requires-Dist: networkx==2.8.8
Requires-Dist: graphviz==0.20.3
